LICENSE
phyelds/__init__.py
phyelds/abstractions/__init__.py
phyelds/calculus/__init__.py
phyelds/calculus/align.py
phyelds/calculus/internal/__init__.py
phyelds/data/__init__.py
phyelds/internal/__init__.py
phyelds/libraries/__init__.py
phyelds/libraries/collect.py
phyelds/libraries/device.py
phyelds/libraries/distances.py
phyelds/libraries/gossip.py
phyelds/libraries/leader_election.py
phyelds/libraries/spreading.py
phyelds/libraries/time.py
phyelds/libraries/utils.py
phyelds/simulator/__init__.py
phyelds/simulator/actions.py
phyelds/simulator/deployments.py
phyelds/simulator/effects.py
phyelds/simulator/exporter.py
phyelds/simulator/neighborhood.py
phyelds/simulator/render.py
phyelds/simulator/runner.py
phyelds-4.3.1.dist-info/LICENSE
phyelds-4.3.1.dist-info/METADATA
phyelds-4.3.1.dist-info/WHEEL
phyelds-4.3.1.dist-info/RECORD
