Metadata-Version: 2.1
Name: phyelds
Version: 4.3.1
Summary: A lightweight Python library to support aggregate computing!
Home-page: https://github.com/phyelds/phyelds
License: Apache-2.0
Author: Davide Domini
Author-email: davide.domini@unibo.it
Requires-Python: >=3.12,<4.0
Classifier: License :: OSI Approved :: Apache Software License
Classifier: Operating System :: OS Independent
Classifier: Programming Language :: Python :: 3
Classifier: Programming Language :: Python :: 3.12
Classifier: Topic :: Software Development :: Libraries :: Python Modules
Requires-Dist: ipython (>=7.34.0,<8.0.0)
Requires-Dist: matplotlib (>=3.10.1,<3.11.0)
Requires-Dist: pandas (>=2.2.3,<3.0.0)
Requires-Dist: pre-commit (>=4.2.0,<5.0.0)
Requires-Dist: pydantic (==2.12.5)
Requires-Dist: vmas (>=1.5.2,<2.0.0)
Requires-Dist: wrapt (>=1.17.2,<1.18.0)
Project-URL: Changelog, https://github.com/phyelds/phyelds/blob/master/CHANGELOG.md
Project-URL: Repository, https://github.com/phyelds/phyelds
